verilog/mult.v
module fulladder
(
 	input x_fa,
 	input y_fa,
 	input cin_fa,
 	output sum_fa, 
 	output carry_fa
);
 
assign {carry_fa, sum_fa} =  cin_fa + y_fa + x_fa;
endmodule

module halfadder
(
	input a_ha,
	input b_ha,
	output sum_ha,
	output carry_ha
);

assign sum_ha = a_ha ^ b_ha;
assign carry_ha = a_ha & b_ha;
endmodule

module mult(product0,product1,product2,product3,product4,product5,product6,product7, A0,A1,A2,A3,B0,B1,B2,B3);

input A0;
input B0;
input A1;
input B1;
input A2;
input B2;
input A3;
input B3;
output product0;
output product1;
output product2;
output product3;
output product4;
output product5;
output product6;
output product7;

wire cha1, sfa1, cfa1, sfa2, cfa2, sfa3, cfa3, sfa4, cfa4, sfa5, cfa5, cfa6, cfa7, cha4, cha3, cha2, sha2;

assign product0 = (A0 & B0);
halfadder h1((A0 & B1),    (A1 & B0), product1, cha1);
fulladder f1((A1 & B1),    (A2 & B0), cha1, sfa1, cfa1);
fulladder f2((A2 & B1),    (A3 & B0), cfa1, sfa2, cfa2);
halfadder h2((A3 & B1), 	     	      cfa2, sha2, cha2);
halfadder h3((A0 & B2), 	        sfa1, product2, cha3);
fulladder f3((A1 & B2), 	        cha3, sfa2, sfa3, cfa3);
fulladder f4((A2 & B2), 	        sha2, cfa3, sfa4, cfa4);
fulladder f5((A3 & B2), 	        cha2, cfa4, sfa5, cfa5);
halfadder h4((A0 & B3), 	        sfa3, product3, cha4);
fulladder f6((A1 & B3),       cha4, sfa4, product4, cfa6);
fulladder f7((A2 & B3),       cfa6, sfa5, product5, cfa7);
fulladder f8((A3 & B3), cfa5, cfa7, product6, product7);
endmodule

verilog/multtb.v
`timescale 1us / 1ns

module multtb;

initial 
begin
	$dumpfile("multtb.vcd");
	$dumpvars(0, multtb);
end

reg inA0; reg inA1; reg inA2; reg inA3; reg inB0; reg inB1; reg inB2; reg inB3;
wire p0; wire p1; wire p2; wire p3; wire p4; wire p5; wire p6; wire p7;

mult uut
(

	.product0(p0),
	.product1(p1),
	.product2(p2),
	.product3(p3),
	.product4(p4),
	.product5(p5),
	.product6(p6),
	.product7(p7),
	.A0(inA0),
	.A1(inA1), 
	.A2(inA2), 
	.A3(inA3), 
	.B0(inB0), 
	.B1(inB1), 
	.B2(inB2), 
	.B3(inB3)  
);
initial begin 
inB3=1'b0;
#128; 
inB3=~inB3;
#128
$stop();
end
initial begin inB2=1'b0; 
forever 
#64 
inB2=~inB2;
end
initial begin inB1=1'b0;
forever 
#32 
inB1=~inB1;
end
initial begin inB0=1'b0; 
forever 
#16 
inB0=~inB0;
end
initial begin inA3=1'b0;
forever 
#8 
inA3=~inA3;
end
initial begin inA2=1'b0; 
forever 
#4 
inA2=~inA2;
end
initial begin inA1=1'b0;
forever 
#2 
inA1=~inA1;
end
initial begin inA0=1'b0; 
forever 
#1 
inA0=~inA0;
end

initial 
begin
	$monitor("time = %2d, P0 = %1b, P1 = %1b, P2 = %1b, P3 = %1b, P4 = %1b, P5 = %1b, P6 = %1b, P7 = %1b", $time, p0, p1, p2, p3, p4, p5, p6, p7);
end

endmodule

verilog/multtb.vcd
$date
	Thu Nov 17 22:25:47 2022
$end
$version
	Icarus Verilog
$end
$timescale
	1ns
$end
$scope module multtb $end
$var wire 1 ! p7 $end
$var wire 1 " p6 $end
$var wire 1 # p5 $end
$var wire 1 $ p4 $end
$var wire 1 % p3 $end
$var wire 1 & p2 $end
$var wire 1 ' p1 $end
$var wire 1 ( p0 $end
$var reg 1 ) inA0 $end
$var reg 1 * inA1 $end
$var reg 1 + inA2 $end
$var reg 1 , inA3 $end
$var reg 1 - inB0 $end
$var reg 1 . inB1 $end
$var reg 1 / inB2 $end
$var reg 1 0 inB3 $end
$scope module uut $end
$var wire 1 ) A0 $end
$var wire 1 * A1 $end
$var wire 1 + A2 $end
$var wire 1 , A3 $end
$var wire 1 - B0 $end
$var wire 1 . B1 $end
$var wire 1 / B2 $end
$var wire 1 0 B3 $end
$var wire 1 ( product0 $end
$var wire 1 1 sha2 $end
$var wire 1 2 sfa5 $end
$var wire 1 3 sfa4 $end
$var wire 1 4 sfa3 $end
$var wire 1 5 sfa2 $end
$var wire 1 6 sfa1 $end
$var wire 1 ! product7 $end
$var wire 1 " product6 $end
$var wire 1 # product5 $end
$var wire 1 $ product4 $end
$var wire 1 % product3 $end
$var wire 1 & product2 $end
$var wire 1 ' product1 $end
$var wire 1 7 cha4 $end
$var wire 1 8 cha3 $end
$var wire 1 9 cha2 $end
$var wire 1 : cha1 $end
$var wire 1 ; cfa7 $end
$var wire 1 < cfa6 $end
$var wire 1 = cfa5 $end
$var wire 1 > cfa4 $end
$var wire 1 ? cfa3 $end
$var wire 1 @ cfa2 $end
$var wire 1 A cfa1 $end
$scope module f1 $end
$var wire 1 B x_fa $end
$var wire 1 C y_fa $end
$var wire 1 6 sum_fa $end
$var wire 1 : cin_fa $end
$var wire 1 A carry_fa $end
$upscope $end
$scope module f2 $end
$var wire 1 A cin_fa $end
$var wire 1 D x_fa $end
$var wire 1 E y_fa $end
$var wire 1 5 sum_fa $end
$var wire 1 @ carry_fa $end
$upscope $end
$scope module f3 $end
$var wire 1 5 cin_fa $end
$var wire 1 F x_fa $end
$var wire 1 8 y_fa $end
$var wire 1 4 sum_fa $end
$var wire 1 ? carry_fa $end
$upscope $end
$scope module f4 $end
$var wire 1 ? cin_fa $end
$var wire 1 G x_fa $end
$var wire 1 1 y_fa $end
$var wire 1 3 sum_fa $end
$var wire 1 > carry_fa $end
$upscope $end
$scope module f5 $end
$var wire 1 > cin_fa $end
$var wire 1 H x_fa $end
$var wire 1 9 y_fa $end
$var wire 1 2 sum_fa $end
$var wire 1 = carry_fa $end
$upscope $end
$scope module f6 $end
$var wire 1 3 cin_fa $end
$var wire 1 I x_fa $end
$var wire 1 7 y_fa $end
$var wire 1 $ sum_fa $end
$var wire 1 < carry_fa $end
$upscope $end
$scope module f7 $end
$var wire 1 2 cin_fa $end
$var wire 1 J x_fa $end
$var wire 1 < y_fa $end
$var wire 1 # sum_fa $end
$var wire 1 ; carry_fa $end
$upscope $end
$scope module f8 $end
$var wire 1 ; cin_fa $end
$var wire 1 K x_fa $end
$var wire 1 = y_fa $end
$var wire 1 " sum_fa $end
$var wire 1 ! carry_fa $end
$upscope $end
$scope module h1 $end
$var wire 1 L a_ha $end
$var wire 1 M b_ha $end
$var wire 1 : carry_ha $end
$var wire 1 ' sum_ha $end
$upscope $end
$scope module h2 $end
$var wire 1 N a_ha $end
$var wire 1 @ b_ha $end
$var wire 1 9 carry_ha $end
$var wire 1 1 sum_ha $end
$upscope $end
$scope module h3 $end
$var wire 1 O a_ha $end
$var wire 1 6 b_ha $end
$var wire 1 8 carry_ha $end
$var wire 1 & sum_ha $end
$upscope $end
$scope module h4 $end
$var wire 1 P a_ha $end
$var wire 1 4 b_ha $end
$var wire 1 7 carry_ha $end
$var wire 1 % sum_ha $end
$upscope $end
$upscope $end
$upscope $end
$enddefinitions $end
#0
$dumpvars
0P
0O
0N
0M
0L
0K
0J
0I
0H
0G
0F
0E
0D
0C
0B
0A
0@
0?
0>
0=
0<
0;
0:
09
08
07
06
05
04
03
02
01
00
0/
0.
0-
0,
0+
0*
0)
0(
0'
0&
0%
0$
0#
0"
0!
$end
#1000
1)
#2000
0)
1*
#3000
1)
#4000
0)
0*
1+
#5000
1)
#6000
0)
1*
#7000
1)
#8000
0)
0*
0+
1,
#9000
1)
#10000
0)
1*
#11000
1)
#12000
0)
0*
1+
#13000
1)
#14000
0)
1*
#15000
1)
#16000
0)
0*
0+
0,
1-
#17000
1(
1)
#18000
1'
0(
1M
0)
1*
#19000
1(
1)
#20000
1&
0'
16
0(
0M
1C
0)
0*
1+
#21000
1(
1)
#22000
1'
0(
1M
0)
1*
#23000
1(
1)
#24000
1%
0&
14
0'
06
15
0(
0M
0C
1E
0)
0*
0+
1,
#25000
1(
1)
#26000
1'
0(
1M
0)
1*
#27000
1(
1)
#28000
1&
0'
16
0(
0M
1C
0)
0*
1+
#29000
1(
1)
#30000
1'
0(
1M
0)
1*
#31000
1(
1)
#32000
0%
0&
04
0'
06
05
0(
0M
0C
0E
0)
0*
0+
0,
0-
1.
#33000
1'
1L
1)
#34000
1&
0'
16
0L
1B
0)
1*
#35000
1'
1L
1)
#36000
1%
0&
14
0'
06
15
0L
0B
1D
0)
0*
1+
#37000
1'
1L
1)
#38000
1&
0'
16
0L
1B
0)
1*
#39000
1'
1L
1)
#40000
0%
1$
0&
04
13
0'
06
05
11
0L
0B
0D
1N
0)
0*
0+
1,
#41000
1'
1L
1)
#42000
1&
0'
16
0L
1B
0)
1*
#43000
1'
1L
1)
#44000
1%
0&
14
0'
06
15
0L
0B
1D
0)
0*
1+
#45000
1'
1L
1)
#46000
1&
0'
16
0L
1B
0)
1*
#47000
1'
1L
1)
#48000
0%
0$
0&
04
03
0'
06
05
01
0L
0B
0D
0N
0)
0*
0+
0,
1-
#49000
1'
1(
1L
1)
#50000
1&
16
0(
0L
1M
1B
0)
1*
#51000
1%
14
0&
15
06
1A
0'
1:
1(
1L
1)
#52000
0$
1&
1%
03
16
0A
14
01
0:
15
0@
0(
0L
0M
0B
1C
1D
0)
0*
1+
#53000
1'
1(
1L
1)
#54000
1$
0%
13
04
11
0&
05
1@
06
1A
0(
0L
1M
1B
0)
1*
#55000
1&
16
0'
1:
1(
1L
1)
#56000
1%
0&
14
1$
0#
06
15
0@
13
02
0:
0A
11
09
0(
0L
0M
0B
0C
0D
1E
1N
0)
0*
0+
1,
#57000
1'
1(
1L
1)
#58000
1&
16
0(
0L
1M
1B
0)
1*
#59000
0$
1#
0%
03
12
04
01
19
0&
05
1@
06
1A
0'
1:
1(
1L
1)
#60000
1&
0%
16
0A
04
0:
05
0(
0L
0M
0B
1C
1D
0)
0*
1+
#61000
1'
1(
1L
1)
#62000
1%
14
0&
15
06
1A
0(
0L
1M
1B
0)
1*
#63000
1&
16
0'
1:
1(
1L
1)
#64000
0%
04
0&
0$
0#
05
06
03
02
0A
0@
0:
01
09
0(
0M
0C
0E
0L
0B
0D
0N
0)
0*
0+
0,
0-
0.
1/
#65000
1&
1O
1)
#66000
1%
0&
14
0O
1F
0)
1*
#67000
1&
1O
1)
#68000
0%
1$
0&
04
13
0O
0F
1G
0)
0*
1+
#69000
1&
1O
1)
#70000
1%
0&
14
0O
1F
0)
1*
#71000
1&
1O
1)
#72000
0%
0$
1#
0&
04
03
12
0O
0F
0G
1H
0)
0*
0+
1,
#73000
1&
1O
1)
#74000
1%
0&
14
0O
1F
0)
1*
#75000
1&
1O
1)
#76000
0%
1$
0&
04
13
0O
0F
1G
0)
0*
1+
#77000
1&
1O
1)
#78000
1%
0&
14
0O
1F
0)
1*
#79000
1&
1O
1)
#80000
0%
0$
0#
0&
04
03
02
0O
0F
0G
0H
0)
0*
0+
0,
1-
#81000
1&
1(
1O
1)
#82000
1%
0&
1'
14
0(
0O
1M
1F
0)
1*
#83000
1&
1(
1O
1)
#84000
0%
1$
0'
04
16
13
0(
0O
0M
0F
1C
1G
0)
0*
1+
#85000
1%
14
0&
18
1(
1O
1)
#86000
0#
1$
02
1%
13
0>
1&
08
1'
14
0?
0(
0O
1M
1F
0)
1*
#87000
1#
0$
12
0%
03
1>
04
1?
0&
18
1(
1O
1)
#88000
1%
14
0?
0$
1#
0"
08
0'
06
03
0>
15
12
0=
0(
0O
0M
0F
0C
0G
1E
1H
0)
0*
0+
1,
#89000
1&
1(
1O
1)
#90000
1$
0%
13
0&
1'
04
1?
0(
0O
1M
1F
0)
1*
#91000
1&
1(
1O
1)
#92000
1#
0"
1%
1$
12
0=
0'
14
0?
16
13
0>
0(
0O
0M
0F
1C
1G
0)
0*
1+
#93000
0#
1"
0$
02
1=
0%
03
1>
04
1?
0&
18
1(
1O
1)
#94000
0%
1&
08
1'
04
0(
0O
1M
1F
0)
1*
#95000
1%
14
0&
18
1(
1O
1)
#96000
0%
04
0$
0#
0"
0?
08
03
0>
02
0=
0'
06
05
0O
0F
0G
0H
0(
0M
0C
0E
0)
0*
0+
0,
0-
1.
#97000
1'
1&
1L
1O
1)
#98000
1%
0'
16
14
0L
0O
1B
1F
0)
1*
#99000
1$
0%
13
04
1?
1'
0&
18
1L
1O
1)
#100000
1%
0#
14
0?
1$
02
0'
08
06
15
13
0>
0L
0O
0B
0F
1D
1G
0)
0*
1+
#101000
1'
1&
1L
1O
1)
#102000
1#
0$
12
0%
03
1>
0'
16
04
1?
0L
0O
1B
1F
0)
1*
#103000
1%
14
1'
0&
18
1L
1O
1)
#104000
1$
0%
13
0>
04
0?
1#
0"
0'
08
06
05
11
12
0=
0L
0O
0B
0F
0D
0G
1N
1H
0)
0*
0+
1,
#105000
1'
1&
1L
1O
1)
#106000
1%
0'
16
14
0L
0O
1B
1F
0)
1*
#107000
0#
1"
0$
02
1=
0%
03
1>
04
1?
1'
0&
18
1L
1O
1)
#108000
1%
14
0?
0$
0'
08
06
15
03
0L
0O
0B
0F
1D
1G
0)
0*
1+
#109000
1'
1&
1L
1O
1)
#110000
1$
0%
13
0'
16
04
1?
0L
0O
1B
1F
0)
1*
#111000
1%
14
1'
0&
18
1L
1O
1)
#112000
0$
0%
03
04
0?
0>
0#
0"
0'
08
06
05
01
02
0=
0L
0O
0B
0F
0D
0G
0N
0H
0)
0*
0+
0,
1-
#113000
1'
1&
1(
1L
1O
1)
#114000
1%
16
14
0(
0L
0O
1M
1B
1F
0)
1*
#115000
1$
15
0%
13
06
1A
04
1?
0'
1:
1&
08
1(
1L
1O
1)
#116000
1%
14
0#
16
0A
01
1$
02
1&
0:
0?
15
0@
13
0>
0(
0L
0O
0M
0B
0F
1C
1D
1G
0)
0*
1+
#117000
1#
0$
12
0%
03
1>
04
1?
1'
0&
18
1(
1L
1O
1)
#118000
0?
11
05
1@
1%
08
06
1A
14
0(
0L
0O
1M
1B
1F
0)
1*
#119000
1$
0%
13
04
1?
18
16
0'
1:
0&
1(
1L
1O
1)
#120000
1$
06
15
0@
1%
13
0>
1#
0"
0&
08
0:
0A
14
0?
11
09
12
0=
0(
0L
0O
0M
0B
0F
0C
0D
0G
1E
1N
1H
0)
0*
0+
1,
#121000
1'
1&
1(
1L
1O
1)
#122000
0#
1"
0$
02
1=
0%
03
1>
16
04
1?
0(
0L
0O
1M
1B
1F
0)
1*
#123000
0#
0>
02
0?
01
19
05
1@
1%
06
1A
14
0'
1:
1&
08
1(
1L
1O
1)
#124000
0%
04
16
0A
1$
1&
0:
05
13
0(
0L
0O
0M
0B
0F
1C
1D
1G
0)
0*
1+
#125000
1%
14
1'
0&
18
1(
1L
1O
1)
#126000
1#
0$
12
15
0%
03
1>
08
06
1A
04
1?
0(
0L
0O
1M
1B
1F
0)
1*
#127000
1%
14
18
16
0'
1:
0&
1(
1L
1O
1)
#128000
0"
05
06
0?
0%
0$
0=
0#
0A
0@
0:
01
09
0&
08
04
03
0>
02
0(
0M
0C
0E
0L
0B
0D
0N
0O
0F
0G
0H
0)
0*
0+
0,
0-
0.
0/
10
#129000
1%
1P
1)
#130000
0%
1$
0P
1I
0)
1*
#131000
1%
1P
1)
#132000
0%
0$
1#
0P
0I
1J
0)
0*
1+
#133000
1%
1P
1)
#134000
0%
1$
0P
1I
0)
1*
#135000
1%
1P
1)
#136000
0%
0$
0#
1"
0P
0I
0J
1K
0)
0*
0+
1,
#137000
1%
1P
1)
#138000
0%
1$
0P
1I
0)
1*
#139000
1%
1P
1)
#140000
0%
0$
1#
0P
0I
1J
0)
0*
1+
#141000
1%
1P
1)
#142000
0%
1$
0P
1I
0)
1*
#143000
1%
1P
1)
#144000
0%
0$
0#
0"
0P
0I
0J
0K
0)
0*
0+
0,
1-
#145000
1%
1(
1P
1)
#146000
0%
1'
1$
0(
0P
1M
1I
0)
1*
#147000
1%
1(
1P
1)
#148000
1&
0%
0'
0$
16
1#
0(
0P
0M
0I
1C
1J
0)
0*
1+
#149000
1%
1(
1P
1)
#150000
0%
1'
1$
0(
0P
1M
1I
0)
1*
#151000
1%
1(
1P
1)
#152000
0&
14
1%
0'
0$
06
0#
15
1"
0(
0P
0M
0I
0C
0J
1E
1K
0)
0*
0+
1,
#153000
1$
0%
17
1(
1P
1)
#154000
0#
1%
07
1'
1$
0<
0(
0P
1M
1I
0)
1*
#155000
1#
0$
1<
0%
17
1(
1P
1)
#156000
1&
1"
0!
1%
07
0'
0$
0<
16
1#
0;
0(
0P
0M
0I
1C
1J
0)
0*
1+
#157000
1$
0%
17
1(
1P
1)
#158000
1"
0!
1#
0;
1%
07
1'
1$
0<
0(
0P
1M
1I
0)
1*
#159000
0"
1!
0#
1;
0$
1<
0%
17
1(
1P
1)
#160000
0&
04
0%
07
0$
0<
0#
0;
0"
0!
0'
06
05
0P
0I
0J
0K
0(
0M
0C
0E
0)
0*
0+
0,
0-
1.
#161000
1'
1%
1L
1P
1)
#162000
1&
0'
0%
16
1$
0L
0P
1B
1I
0)
1*
#163000
1'
1%
1L
1P
1)
#164000
0&
14
0'
1%
06
0$
15
1#
0L
0P
0B
0I
1D
1J
0)
0*
1+
#165000
1$
1'
0%
17
1L
1P
1)
#166000
0"
1&
1#
0;
0'
1%
07
16
1$
0<
0L
0P
1B
1I
0)
1*
#167000
1"
0#
1;
0$
1<
1'
0%
17
1L
1P
1)
#168000
0&
04
13
0'
0%
07
06
1$
0<
05
0#
0;
11
1"
0!
0L
0P
0B
0I
0D
0J
1N
1K
0)
0*
0+
1,
#169000
1'
1%
1L
1P
1)
#170000
1&
1#
0'
0%
16
0$
1<
0L
0P
1B
1I
0)
1*
#171000
1'
1%
1L
1P
1)
#172000
0&
14
1"
0!
0'
1%
06
1$
0<
15
1#
0;
0L
0P
0B
0I
1D
1J
0)
0*
1+
#173000
0"
1!
0#
1;
0$
1<
1'
0%
17
1L
1P
1)
#174000
1&
0'
1%
07
16
0$
0L
0P
1B
1I
0)
1*
#175000
1$
1'
0%
17
1L
1P
1)
#176000
0<
0&
04
03
0'
0%
07
06
0$
05
0#
0;
01
0"
0!
0L
0P
0B
0I
0D
0J
0N
0K
0)
0*
0+
0,
1-
#177000
1'
1%
1(
1L
1P
1)
#178000
1&
0%
16
1$
0(
0L
0P
1M
1B
1I
0)
1*
#179000
1#
0$
1<
17
14
0&
15
06
1A
0'
1:
0%
1(
1L
1P
1)
#180000
1&
03
16
0A
14
01
0"
1%
07
0:
0$
0<
15
0@
1#
0;
0(
0L
0P
0M
0B
0I
1C
1D
1J
0)
0*
1+
#181000
1$
1'
0%
17
1(
1L
1P
1)
#182000
13
04
11
1"
0&
05
1@
0#
1;
0%
07
06
1A
0$
1<
0(
0L
0P
1M
1B
1I
0)
1*
#183000
1&
16
0'
1:
1%
1(
1L
1P
1)
#184000
0&
14
06
15
0@
13
02
1%
0:
0A
1$
0<
0#
0;
11
09
1"
0!
0(
0L
0P
0M
0B
0I
0C
0D
0J
1E
1N
1K
0)
0*
0+
1,
#185000
1#
0$
1<
1'
0%
17
1(
1L
1P
1)
#186000
1&
1%
07
16
0$
0(
0L
0P
1M
1B
1I
0)
1*
#187000
1"
0!
0<
1#
0;
03
12
04
01
19
0&
05
1@
06
1A
1$
0'
1:
1%
07
1(
1L
1P
1)
#188000
1&
16
0A
04
0"
1!
0%
0:
0$
05
0#
1;
0(
0L
0P
0M
0B
0I
1C
1D
1J
0)
0*
1+
#189000
1'
1%
1(
1L
1P
1)
#190000
14
0&
15
1%
06
1A
1$
0(
0L
0P
1M
1B
1I
0)
1*
#191000
1&
1#
16
0$
1<
0'
1:
0%
17
1(
1L
1P
1)
#192000
04
0&
0;
05
06
03
02
0%
07
0$
0<
0#
0"
0!
0A
0@
0:
01
09
0P
0I
0J
0K
0(
0M
0C
0E
0L
0B
0D
0N
0)
0*
0+
0,
0-
0.
1/
#193000
1&
1%
1O
1P
1)
#194000
0&
14
1$
0O
0P
1F
1I
0)
1*
#195000
1#
0$
1<
1&
0%
17
1O
1P
1)
#196000
1$
0<
0"
0&
07
04
13
1#
0;
0O
0P
0F
0I
1G
1J
0)
0*
1+
#197000
1&
1%
1O
1P
1)
#198000
1"
0#
1;
0&
14
0$
1<
0O
0P
1F
1I
0)
1*
#199000
1$
1&
0%
17
1O
1P
1)
#200000
1#
0;
0$
0<
0&
07
04
03
12
1"
0!
0O
0P
0F
0I
0G
0J
1H
1K
0)
0*
0+
1,
#201000
1&
1%
1O
1P
1)
#202000
0&
14
1$
0O
0P
1F
1I
0)
1*
#203000
0"
1!
0#
1;
0$
1<
1&
0%
17
1O
1P
1)
#204000
1$
0<
0&
07
04
13
0#
0O
0P
0F
0I
1G
1J
0)
0*
1+
#205000
1&
1%
1O
1P
1)
#206000
1#
0&
14
0$
1<
0O
0P
1F
1I
0)
1*
#207000
1$
1&
0%
17
1O
1P
1)
#208000
0#
0$
0<
0;
0&
07
04
03
02
0"
0!
0O
0P
0F
0I
0G
0J
0H
0K
0)
0*
0+
0,
1-
#209000
1&
1%
1(
1O
1P
1)
#210000
0&
1'
14
1$
0(
0O
0P
1M
1F
1I
0)
1*
#211000
1#
0$
1<
1&
0%
17
1(
1O
1P
1)
#212000
1$
0<
0"
07
0'
04
16
13
1#
0;
0(
0O
0P
0M
0F
0I
1C
1G
1J
0)
0*
1+
#213000
1"
0#
1;
0$
1<
17
14
0&
18
0%
1(
1O
1P
1)
#214000
1%
1<
02
13
0>
1&
08
07
1'
14
0?
0$
0(
0O
0P
1M
1F
1I
0)
1*
#215000
0<
12
03
1>
04
1?
1$
0&
18
1%
07
1(
1O
1P
1)
#216000
0$
1#
14
0?
08
1%
0'
06
03
0>
0;
15
12
0=
1"
0!
0(
0O
0P
0M
0F
0I
0C
0G
0J
1E
1H
1K
0)
0*
0+
1,
#217000
1$
1&
0%
17
1(
1O
1P
1)
#218000
0"
1!
13
0#
1;
0&
07
1'
04
1?
0$
1<
0(
0O
0P
1M
1F
1I
0)
1*
#219000
1&
1%
1(
1O
1P
1)
#220000
1!
1$
1;
0"
12
0=
0'
14
0?
0<
16
13
0>
0#
0(
0O
0P
0M
0F
0I
1C
1G
1J
0)
0*
1+
#221000
0;
0"
02
1=
03
1>
1#
04
1?
0$
0<
0&
18
1%
07
1(
1O
1P
1)
#222000
0%
1&
08
1'
04
1$
0(
0O
0P
1M
1F
1I
0)
1*
#223000
1"
0#
1;
0$
1<
17
14
0&
18
0%
1(
1O
1P
1)
#224000
0;
04
0$
0<
0!
0?
08
0%
07
03
0>
02
0=
0"
0'
06
05
0O
0P
0F
0I
0G
0J
0H
0K
0(
0M
0C
0E
0)
0*
0+
0,
0-
1.
#225000
1'
1&
1%
1L
1O
1P
1)
#226000
0'
16
14
1$
0L
0O
0P
1B
1F
1I
0)
1*
#227000
13
1#
04
1?
0$
1<
1'
0&
18
1%
07
1L
1O
1P
1)
#228000
1$
14
0?
02
0"
0'
08
1%
06
0<
15
13
0>
1#
0;
0L
0O
0P
0B
0F
0I
1D
1G
1J
0)
0*
1+
#229000
1"
0#
1;
0$
1<
1'
1&
0%
17
1L
1O
1P
1)
#230000
0<
12
03
1>
0'
07
16
04
1?
1$
0L
0O
0P
1B
1F
1I
0)
1*
#231000
1#
0$
1<
17
14
1'
0&
18
0%
1L
1O
1P
1)
#232000
13
0>
04
1#
0?
0;
0'
08
0%
07
06
1$
0<
05
11
12
0=
1"
0!
0L
0O
0P
0B
0F
0I
0D
0G
0J
1N
1H
1K
0)
0*
0+
1,
#233000
1'
1&
1%
1L
1O
1P
1)
#234000
0"
1!
0#
1;
0'
16
14
0$
1<
0L
0O
0P
1B
1F
1I
0)
1*
#235000
0;
0"
0<
02
1=
03
1>
04
1?
1$
1'
0&
18
1%
07
1L
1O
1P
1)
#236000
0$
14
0?
0'
08
1%
06
15
03
1#
0L
0O
0P
0B
0F
0I
1D
1G
1J
0)
0*
1+
#237000
1$
1'
1&
0%
17
1L
1O
1P
1)
#238000
1"
13
0#
1;
0'
07
16
04
1?
0$
1<
0L
0O
0P
1B
1F
1I
0)
1*
#239000
1$
17
14
1'
0&
18
0%
1L
1O
1P
1)
#240000
0;
03
04
0<
0?
0>
0!
0'
08
0%
07
06
0$
05
01
02
0=
0"
0L
0O
0P
0B
0F
0I
0D
0G
0J
0N
0H
0K
0)
0*
0+
0,
1-
#241000
1'
1&
1%
1(
1L
1O
1P
1)
#242000
16
14
1$
0(
0L
0O
0P
1M
1B
1F
1I
0)
1*
#243000
15
13
1#
06
1A
04
1?
0$
1<
0'
1:
1&
08
1%
07
1(
1L
1O
1P
1)
#244000
1$
14
16
0A
01
02
0"
1&
1%
0:
0?
0<
15
0@
13
0>
1#
0;
0(
0L
0O
0P
0M
0B
0F
0I
1C
1D
1G
1J
0)
0*
1+
#245000
12
1"
03
1>
0#
1;
04
1?
0$
0<
1'
0&
18
1%
07
1(
1L
1O
1P
1)
#246000
0?
11
05
1@
08
06
1A
14
1$
0(
0L
0O
0P
1M
1B
1F
1I
0)
1*
#247000
13
04
1?
18
1#
16
0$
1<
0'
1:
0&
1%
07
1(
1L
1O
1P
1)
#248000
1#
06
15
0@
13
0>
0;
0&
08
0:
0A
14
0?
1$
0<
11
09
12
0=
1"
0!
0(
0L
0O
0P
0M
0B
0F
0I
0C
0D
0G
0J
1E
1N
1H
1K
0)
0*
0+
1,
#249000
0"
1!
0#
1;
0$
1<
1'
1&
0%
17
1(
1L
1O
1P
1)
#250000
0;
0"
0<
02
1=
03
1>
07
16
04
1?
1$
0(
0L
0O
0P
1M
1B
1F
1I
0)
1*
#251000
0"
0;
0>
02
1#
0?
01
19
0$
1<
05
1@
17
06
1A
14
0'
1:
1&
08
0%
1(
1L
1O
1P
1)
#252000
04
1$
0<
16
0A
0"
1&
0%
07
0:
05
13
1#
0;
0(
0L
0O
0P
0M
0B
0F
0I
1C
1D
1G
1J
0)
0*
1+
#253000
1"
0#
1;
0$
1<
17
14
1'
0&
18
0%
1(
1L
1O
1P
1)
#254000
0<
12
15
03
1>
08
07
06
1A
04
1?
1$
0(
0L
0O
0P
1M
1B
1F
1I
0)
1*
#255000
1#
0$
1<
17
14
18
16
0'
1:
0&
0%
1(
1L
1O
1P
1)
